strava_mcp_server/__init__.py
strava_mcp_server/py.typed
strava_mcp_server/server.py
strava_mcp_server-0.1.3.dist-info/METADATA
strava_mcp_server-0.1.3.dist-info/WHEEL
strava_mcp_server-0.1.3.dist-info/entry_points.txt
strava_mcp_server-0.1.3.dist-info/licenses/LICENSE
strava_mcp_server-0.1.3.dist-info/RECORD
