Metadata-Version: 2.4
Name: strava-mcp-server
Version: 0.1.3
Summary: MCP server for Strava API integration
Project-URL: Homepage, https://github.com/tomek-korbak/strava-mcp-server
Project-URL: Bug Tracker, https://github.com/tomek-korbak/strava-mcp-server/issues
Author-email: Tomek Korbak <tomasz.korbak@gmail.com>
License-File: LICENSE
Classifier: Development Status :: 4 - Beta
Classifier: Intended Audience :: Developers
Classifier: License :: OSI Approved :: MIT License
Classifier: Programming Language :: Python :: 3
Classifier: Programming Language :: Python :: 3.12
Classifier: Topic :: Software Development :: Libraries :: Python Modules
Requires-Python: >=3.12
Requires-Dist: fastmcp>=0.1.0
Requires-Dist: httpx>=0.24.0
Requires-Dist: python-dotenv>=1.0.0
Requires-Dist: rich>=13.0.0
Provides-Extra: dev
Requires-Dist: mypy>=1.0.0; extra == 'dev'
Requires-Dist: ruff>=0.1.0; extra == 'dev'
